py_diff_pdf2/__init__.py
py_diff_pdf2/main.py
py_diff_pdf2/libs/__init__.py
py_diff_pdf2/libs/diff-pdf.exe
py_diff_pdf2/libs/libLerc.dll
py_diff_pdf2/libs/libbrotlicommon.dll
py_diff_pdf2/libs/libbrotlidec.dll
py_diff_pdf2/libs/libbz2-1.dll
py_diff_pdf2/libs/libcairo-2.dll
py_diff_pdf2/libs/libcrypto-3-x64.dll
py_diff_pdf2/libs/libcurl-4.dll
py_diff_pdf2/libs/libdeflate.dll
py_diff_pdf2/libs/libexpat-1.dll
py_diff_pdf2/libs/libffi-8.dll
py_diff_pdf2/libs/libfontconfig-1.dll
py_diff_pdf2/libs/libfreetype-6.dll
py_diff_pdf2/libs/libgcc_s_seh-1.dll
py_diff_pdf2/libs/libgio-2.0-0.dll
py_diff_pdf2/libs/libglib-2.0-0.dll
py_diff_pdf2/libs/libgmodule-2.0-0.dll
py_diff_pdf2/libs/libgobject-2.0-0.dll
py_diff_pdf2/libs/libgraphite2.dll
py_diff_pdf2/libs/libharfbuzz-0.dll
py_diff_pdf2/libs/libiconv-2.dll
py_diff_pdf2/libs/libidn2-0.dll
py_diff_pdf2/libs/libintl-8.dll
py_diff_pdf2/libs/libjbig-0.dll
py_diff_pdf2/libs/libjpeg-8.dll
py_diff_pdf2/libs/liblcms2-2.dll
py_diff_pdf2/libs/liblzma-5.dll
py_diff_pdf2/libs/libnghttp2-14.dll
py_diff_pdf2/libs/libnghttp3-9.dll
py_diff_pdf2/libs/libnspr4.dll
py_diff_pdf2/libs/libopenjp2-7.dll
py_diff_pdf2/libs/libpcre2-8-0.dll
py_diff_pdf2/libs/libpixman-1-0.dll
py_diff_pdf2/libs/libplc4.dll
py_diff_pdf2/libs/libplds4.dll
py_diff_pdf2/libs/libpng16-16.dll
py_diff_pdf2/libs/libpoppler-143.dll
py_diff_pdf2/libs/libpoppler-glib-8.dll
py_diff_pdf2/libs/libpsl-5.dll
py_diff_pdf2/libs/libsharpyuv-0.dll
py_diff_pdf2/libs/libssh2-1.dll
py_diff_pdf2/libs/libssl-3-x64.dll
py_diff_pdf2/libs/libstdc++-6.dll
py_diff_pdf2/libs/libtiff-6.dll
py_diff_pdf2/libs/libunistring-5.dll
py_diff_pdf2/libs/libwebp-7.dll
py_diff_pdf2/libs/libwinpthread-1.dll
py_diff_pdf2/libs/libzstd.dll
py_diff_pdf2/libs/nss3.dll
py_diff_pdf2/libs/nssutil3.dll
py_diff_pdf2/libs/smime3.dll
py_diff_pdf2/libs/wxbase30u_gcc_custom.dll
py_diff_pdf2/libs/wxmsw30u_core_gcc_custom.dll
py_diff_pdf2/libs/zlib1.dll
py_diff_pdf2/libs/fonts/fonts.conf
py_diff_pdf2-1.1.5.dist-info/METADATA
py_diff_pdf2-1.1.5.dist-info/WHEEL
py_diff_pdf2-1.1.5.dist-info/licenses/LICENSE
py_diff_pdf2-1.1.5.dist-info/RECORD
