Metadata-Version: 2.4
Name: py_diff_pdf2
Version: 1.1.5
Summary: pdf文档比对
Project-URL: Homepage, https://github.com/lwinhong/py-diff-pdf
Project-URL: Issues, https://github.com/lwinhong/py-diff-pdf/issues
Author-email: lwinhong <80469181@qq.com>
License: Copyright (c) 2018 The Python Packaging Authority
License-File: LICENSE
Classifier: License :: OSI Approved :: MIT License
Classifier: Operating System :: OS Independent
Classifier: Programming Language :: Python :: 3
Requires-Python: >=3.6
